{"municipalities": [{"ymax": 9753, "g": "116.395645,39.929986|12", "n": "北京", "xmax": 25550, "xmin": 25097, "ymin": 9293}, {"ymax": 7273, "g": "121.487899,31.249162|12", "n": "上海", "xmax": 26526, "xmin": 26278, "ymin": 6970}, {"ymax": 9523, "g": "117.210813,39.14393|12", "n": "天津", "xmax": 25672, "xmin": 25376, "ymin": 9047}, {"ymax": 7358, "g": "106.530635,29.544606|12", "n": "重庆", "xmax": 23961, "xmin": 22893, "ymin": 6346}], "other": [{"ymax": 5007, "g": "114.186124,22.293586|11", "n": "香港", "xmax": 24897, "xmin": 24748, "ymin": 4906}, {"ymax": 4925, "g": "113.557519,22.204118|13", "n": "澳门", "xmax": 24702, "xmin": 24686, "ymin": 4898}, {"ymax": 5652, "g": "120.961454,23.80406|8", "n": "台湾", "xmax": 26524, "xmin": 26102, "ymin": 4851}], "provinces": [{"ymin": 6651, "ymax": 7993, "g": "117.284546,31.914868|8", "n": "宣城", "xmax": 26015, "xmin": 24979, "cities": [{"ymax": 7443, "g": "117.282699,31.866942|12", "n": "合肥", "xmax": 25632, "xmin": 25372, "ymin": 7180}, {"ymax": 7121, "g": "117.058739,30.537898|13", "n": "安庆", "xmax": 25601, "xmin": 25170, "ymin": 6747}, {"ymax": 7693, "g": "117.35708,32.929499|13", "n": "蚌埠", "xmax": 25673, "xmin": 25382, "ymin": 7489}, {"ymax": 7841, "g": "115.787928,33.871211|13", "n": "亳州", "xmax": 25403, "xmin": 25123, "ymin": 7527}, {"ymax": 7321, "g": "117.88049,31.608733|13", "n": "巢湖", "xmax": 25767, "xmin": 25446, "ymin": 7037}, {"ymax": 7014, "g": "117.494477,30.660019|14", "n": "池州", "xmax": 25685, "xmin": 25363, "ymin": 6693}, {"ymax": 7619, "g": "118.32457,32.317351|13", "n": "滁州", "xmax": 25924, "xmin": 25474, "ymin": 7269}, {"ymax": 7714, "g": "115.820932,32.901211|13", "n": "阜阳", "xmax": 25360, "xmin": 24979, "ymin": 7410}, {"ymax": 7851, "g": "116.791447,33.960023|13", "n": "淮北", "xmax": 25441, "xmin": 25308, "ymin": 7635}, {"ymax": 7564, "g": "117.018639,32.642812|13", "n": "淮南", "xmax": 25486, "xmin": 25301, "ymin": 7406}, {"ymax": 6931, "g": "118.29357,29.734435|13", "n": "黄山", "xmax": 25853, "xmin": 25483, "ymin": 6651}, {"ymax": 7476, "g": "116.505253,31.755558|13", "n": "六安", "xmax": 25495, "xmin": 25085, "ymin": 7055}, {"ymax": "", "g": "118.515882,31.688528|13", "n": "马鞍山", "xmax": "", "xmin": "", "ymin": ""}, {"ymax": 7993, "g": "116.988692,33.636772|13", "n": "宿州", "xmax": 25698, "xmin": 25257, "ymin": 7634}, {"ymax": 7085, "g": "117.819429,30.94093|14", "n": "铜陵", "xmax": 25693, "xmin": 25592, "ymin": 6989}, {"ymax": 7187, "g": "118.384108,31.36602|12", "n": "芜湖", "xmax": 25816, "xmin": 25650, "ymin": 6962}, {"ymax": 7130, "g": "118.752096,30.951642|13", "n": "宣城", "xmax": 26015, "xmin": 25650, "ymin": 6788}]}, {"ymin": 5240, "ymax": 6382, "g": "117.984943,26.050118|8", "n": "漳州", "xmax": 26186, "xmin": 25190, "cities": [{"ymax": 5976, "g": "119.330221,26.047125|12", "n": "福州", "xmax": 26208, "xmin": 25740, "ymin": 5632}, {"ymax": 5830, "g": "117.017997,25.078685|13", "n": "龙岩", "xmax": 25603, "xmin": 25190, "ymin": 5432}, {"ymax": 6384, "g": "118.181883,26.643626|13", "n": "南平", "xmax": 25934, "xmin": 25440, "ymin": 5883}, {"ymax": 6228, "g": "119.542082,26.656527|14", "n": "宁德", "xmax": 26255, "xmin": 25776, "ymin": 5892}, {"ymax": 5762, "g": "119.077731,25.44845|13", "n": "莆田", "xmax": 26031, "xmin": 25755, "ymin": 5568}, {"ymax": 5805, "g": "118.600362,24.901652|12", "n": "泉州", "xmax": 25889, "xmin": 25565, "ymin": 5416}, {"ymax": 6095, "g": "117.642194,26.270835|14", "n": "三明", "xmax": 25803, "xmin": 25305, "ymin": 5696}, {"ymax": 5560, "g": "118.103886,24.489231|12", "n": "厦门", "xmax": 25756, "xmin": 25632, "ymin": 5435}, {"ymax": 5628, "g": "117.676205,24.517065|12", "n": "漳州", "xmax": 25710, "xmin": 25418, "ymin": 5238}]}, {"ymin": 7459, "ymax": 10258, "g": "102.457625,38.103267|6", "n": "张掖", "xmax": 23638, "xmin": 20074, "cities": [{"ymax": 8630, "g": "103.823305,36.064226|12", "n": "兰州", "xmax": 22738, "xmin": 22309, "ymin": 8237}, {"ymax": 8794, "g": "104.171241,36.546682|13", "n": "白银", "xmax": 22944, "xmin": 22516, "ymin": 8195}, {"ymax": 8363, "g": "104.626638,35.586056|13", "n": "定西", "xmax": 22971, "xmin": 22497, "ymin": 7855}, {"ymax": 8243, "g": "102.917442,34.992211|14", "n": "甘南州", "xmax": 22779, "xmin": 21909, "ymin": 7590}, {"ymax": "", "g": "98.281635,39.802397|13", "n": "嘉峪关", "xmax": "", "xmin": "", "ymin": ""}, {"ymax": 9170, "g": "102.208126,38.516072|13", "n": "金昌", "xmax": 22338, "xmin": 22052, "ymin": 8900}, {"ymax": 10258, "g": "98.508415,39.741474|13", "n": "酒泉", "xmax": 21787, "xmin": 20074, "ymin": 8922}, {"ymax": 8408, "g": "103.215249,35.598514|13", "n": "临夏州", "xmax": 22582, "xmin": 22327, "ymin": 8070}, {"ymax": 7962, "g": "104.934573,33.39448|14", "n": "陇南", "xmax": 23175, "xmin": 22618, "ymin": 7459}, {"ymax": 8284, "g": "106.688911,35.55011|13", "n": "平凉", "xmax": 23453, "xmin": 22905, "ymin": 8054}, {"ymax": 8664, "g": "107.644227,35.726801|13", "n": "庆阳", "xmax": 23638, "xmin": 23127, "ymin": 8149}, {"ymax": 8132, "g": "105.736932,34.584319|13", "n": "天水", "xmax": 23203, "xmin": 22739, "ymin": 7843}, {"ymax": 9299, "g": "102.640147,37.933172|13", "n": "武威", "xmax": 22658, "xmin": 22142, "ymin": 8554}, {"ymax": 9418, "g": "100.459892,38.93932|13", "n": "张掖", "xmax": 22225, "xmin": 21175, "ymin": 8786}]}, {"ymin": 4425, "ymax": 5706, "g": "113.394818,23.408004|8", "n": "珠海", "xmax": 25518, "xmin": 23837, "cities": [{"ymax": 5328, "g": "113.30765,23.120049|12", "n": "广州", "xmax": 24800, "xmin": 24561, "ymin": 4995}, {"ymax": 5400, "g": "116.630076,23.661812|13", "n": "潮州", "xmax": 25484, "xmin": 25302, "ymin": 5209}, {"ymax": 5142, "g": "113.763434,23.043024|12", "n": "东莞", "xmax": 24843, "xmin": 24683, "ymin": 5028}, {"ymax": 5243, "g": "113.134026,23.035095|13", "n": "佛山", "xmax": 24655, "xmin": 24437, "ymin": 5025}, {"ymax": 5530, "g": "114.713721,23.757251|12", "n": "河源", "xmax": 25133, "xmin": 24840, "ymin": 5147}, {"ymax": 5335, "g": "114.410658,23.11354|12", "n": "惠州", "xmax": 25096, "xmin": 24747, "ymin": 4962}, {"ymax": 5074, "g": "113.078125,22.575117|13", "n": "江门", "xmax": 24627, "xmin": 24353, "ymin": 4745}, {"ymax": 5291, "g": "116.379501,23.547999|13", "n": "揭阳", "xmax": 25360, "xmin": 25138, "ymin": 5073}, {"ymax": 5039, "g": "110.931245,21.668226|13", "n": "茂名", "xmax": 24284, "xmin": 23988, "ymin": 4721}, {"ymax": 5567, "g": "116.126403,24.304571|13", "n": "梅州", "xmax": 25427, "xmin": 25073, "ymin": 5196}, {"ymax": 5630, "g": "113.040773,23.698469|13", "n": "清远", "xmax": 24769, "xmin": 24337, "ymin": 5216}, {"ymax": 5261, "g": "116.72865,23.383908|13", "n": "汕头", "xmax": 25518, "xmin": 25276, "ymin": 5118}, {"ymax": 5220, "g": "115.372924,22.778731|14", "n": "汕尾", "xmax": 25271, "xmin": 24987, "ymin": 5018}, {"ymax": 5706, "g": "113.594461,24.80296|13", "n": "韶关", "xmax": 24949, "xmin": 24538, "ymin": 5318}, {"ymax": 5074, "g": "114.025974,22.546054|12", "n": "深圳", "xmax": 24929, "xmin": 24717, "ymin": 4929}, {"ymax": 5033, "g": "111.97701,21.871517|14", "n": "阳江", "xmax": 24433, "xmin": 24196, "ymin": 4751}, {"ymax": 5185, "g": "112.050946,22.937976|13", "n": "云浮", "xmax": 24466, "xmin": 24147, "ymin": 4962}, {"ymax": 4856, "g": "110.365067,21.257463|13", "n": "湛江", "xmax": 24153, "xmin": 23837, "ymin": 4425}, {"ymax": 5439, "g": "112.479653,23.078663|13", "n": "肇庆", "xmax": 24544, "xmin": 24214, "ymin": 5055}, {"ymax": 5056, "g": "113.42206,22.545178|12", "n": "中山", "xmax": 24720, "xmin": 24604, "ymin": 4916}, {"ymax": 4981, "g": "113.562447,22.256915|13", "n": "珠海", "xmax": 24877, "xmin": 24583, "ymin": 4823}]}, {"ymin": 4612, "ymax": 5915, "g": "108.924274,23.552255|7", "n": "玉林", "xmax": 24366, "xmin": 22711, "cities": [{"ymax": 5914, "g": "110.26092,25.262901|12", "n": "桂林", "xmax": 24242, "xmin": 23834, "ymin": 5405}, {"ymax": 5352, "g": "108.297234,22.806493|12", "n": "南宁", "xmax": 23835, "xmin": 23337, "ymin": 4922}, {"ymax": 5834, "g": "109.422402,24.329053|12", "n": "柳州", "xmax": 23956, "xmin": 23610, "ymin": 5322}, {"ymax": 4856, "g": "109.122628,21.472718|13", "n": "北海", "xmax": 23872, "xmin": 23667, "ymin": 4612}, {"ymax": 5192, "g": "107.357322,22.415455|14", "n": "崇左", "xmax": 23507, "xmin": 23170, "ymin": 4780}, {"ymax": 4962, "g": "108.351791,21.617398|15", "n": "防城港", "xmax": 23615, "xmin": 23371, "ymin": 4754}, {"ymax": 5606, "g": "106.631821,23.901512|13", "n": "百色", "xmax": 23457, "xmin": 22711, "ymin": 5075}, {"ymax": 5354, "g": "109.613708,23.103373|13", "n": "贵港", "xmax": 24062, "xmin": 23745, "ymin": 5027}, {"ymax": 5728, "g": "108.069948,24.699521|14", "n": "河池", "xmax": 23735, "xmin": 23172, "ymin": 5239}, {"ymax": 5618, "g": "111.552594,24.411054|14", "n": "贺州", "xmax": 24366, "xmin": 24042, "ymin": 5262}, {"ymax": 5455, "g": "109.231817,23.741166|14", "n": "来宾", "xmax": 24017, "xmin": 23574, "ymin": 5172}, {"ymax": 5034, "g": "108.638798,21.97335|13", "n": "钦州", "xmax": 23889, "xmin": 23523, "ymin": 4759}, {"ymax": 5440, "g": "111.305472,23.485395|13", "n": "梧州", "xmax": 24280, "xmin": 23988, "ymin": 5016}, {"ymax": 5138, "g": "110.151676,22.643974|14", "n": "玉林", "xmax": 24113, "xmin": 23818, "ymin": 4790}]}, {"ymin": 5491, "ymax": 6608, "g": "106.734996,26.902826|8", "n": "黔南州", "xmax": 23822, "xmin": 22527, "cities": [{"ymax": 6150, "g": "106.709177,26.629907|12", "n": "贵阳", "xmax": 23326, "xmin": 23075, "ymin": 5866}, {"ymax": 5972, "g": "105.92827,26.228595|13", "n": "安顺", "xmax": 23172, "xmin": 22884, "ymin": 5667}, {"ymax": 6252, "g": "105.300492,27.302612|14", "n": "毕节地区", "xmax": 23206, "xmin": 22526, "ymin": 5908}, {"ymax": 6044, "g": "104.852087,26.591866|13", "n": "六盘水", "xmax": 22987, "xmin": 22680, "ymin": 5659}, {"ymax": 6574, "g": "109.196161,27.726271|14", "n": "铜仁地区", "xmax": 23803, "xmin": 23429, "ymin": 6093}, {"ymax": 6608, "g": "106.93126,27.699961|13", "n": "遵义", "xmax": 23529, "xmin": 22963, "ymin": 6096}, {"ymax": 5864, "g": "104.900558,25.095148|11", "n": "黔西南州", "xmax": 23163, "xmin": 22728, "ymin": 5491}, {"ymax": 6192, "g": "107.985353,26.583992|11", "n": "黔东南州", "xmax": 23822, "xmin": 23330, "ymin": 5655}, {"ymax": 6181, "g": "107.523205,26.264536|11", "n": "黔南州", "xmax": 23549, "xmin": 23094, "ymin": 5596}]}, {"ymin": 3990, "ymax": 4448, "g": "109.733755,19.180501|9", "n": "五指山", "xmax": 24142, "xmin": 23615, "cities": [{"ymax": 4453, "g": "110.330802,20.022071|13", "n": "海口", "xmax": 24072, "xmin": 23933, "ymin": 4302}, {"ymax": "", "g": "109.358586,19.216056|12", "n": "白沙", "xmax": "", "xmin": "", "ymin": ""}, {"ymax": "", "g": "109.656113,18.597592|12", "n": "保亭", "xmax": "", "xmin": "", "ymin": ""}, {"ymax": "", "g": "109.0113,19.222483|12", "n": "昌江", "xmax": "", "xmin": "", "ymin": ""}, {"ymax": 4400, "g": "109.413973,19.571153|13", "n": "儋州", "xmax": 23867, "xmin": 23677, "ymin": 4223}, {"ymax": 4432, "g": "109.996736,19.693135|13", "n": "澄迈", "xmax": 23974, "xmin": 23858, "ymin": 4268}, {"ymax": 4266, "g": "108.85101,18.998161|13", "n": "东方", "xmax": 23727, "xmin": 23607, "ymin": 4117}, {"ymax": 4349, "g": "110.32009,19.490991|13", "n": "定安", "xmax": 24038, "xmin": 23944, "ymin": 4231}, {"ymax": 4290, "g": "110.414359,19.21483|13", "n": "琼海", "xmax": 24074, "xmin": 23944, "ymin": 4177}, {"ymax": "", "g": "109.861849,19.039771|12", "n": "琼中", "xmax": "", "xmin": "", "ymin": ""}, {"ymax": "", "g": "109.062698,18.658614|12", "n": "乐东", "xmax": "", "xmin": "", "ymin": ""}, {"ymax": 4421, "g": "109.724101,19.805922|13", "n": "临高", "xmax": 23895, "xmin": 23807, "ymin": 4314}, {"ymax": "", "g": "109.948661,18.575985|12", "n": "陵水", "xmax": "", "xmin": "", "ymin": ""}, {"ymax": 4096, "g": "109.522771,18.257776|12", "n": "三亚", "xmax": 23876, "xmin": 23685, "ymin": 3981}, {"ymax": 4318, "g": "110.063364,19.347749|13", "n": "屯昌", "xmax": 23972, "xmin": 23879, "ymin": 4212}, {"ymax": 4206, "g": "110.292505,18.839886|13", "n": "万宁", "xmax": 24051, "xmin": 23920, "ymin": 4085}, {"ymax": 4469, "g": "110.780909,19.750947|13", "n": "文昌", "xmax": 24204, "xmin": 24018, "ymin": 4255}, {"ymax": "", "g": "109.51775,18.831306|13", "n": "五指山", "xmax": "", "xmin": "", "ymin": ""}]}, {"ymin": 8365, "ymax": 10206, "g": "115.661434,38.61384|7", "n": "张家口", "xmax": 26062, "xmin": 24670, "cities": [{"ymax": 9105, "g": "114.522082,38.048958|12", "n": "石家庄", "xmax": 25110, "xmin": 24684, "ymin": 8740}, {"ymax": 9437, "g": "115.49481,38.886565|13", "n": "保定", "xmax": 25295, "xmin": 24737, "ymin": 8959}, {"ymax": 9155, "g": "116.863806,38.297615|13", "n": "沧州", "xmax": 25647, "xmin": 25157, "ymin": 8749}, {"ymax": 10206, "g": "117.933822,40.992521|14", "n": "承德", "xmax": 25929, "xmin": 25202, "ymin": 9505}, {"ymax": 8627, "g": "114.482694,36.609308|13", "n": "邯郸", "xmax": 25110, "xmin": 24670, "ymin": 8365}, {"ymax": 8995, "g": "115.686229,37.746929|13", "n": "衡水", "xmax": 25345, "xmin": 25046, "ymin": 8637}, {"ymax": 9345, "g": "116.703602,39.518611|13", "n": "廊坊", "xmax": 25424, "xmin": 25247, "ymin": 9024}, {"ymax": 9625, "g": "119.604368,39.945462|12", "n": "秦皇岛", "xmax": 26062, "xmin": 25781, "ymin": 9290}, {"ymax": 9583, "g": "118.183451,39.650531|13", "n": "唐山", "xmax": 25972, "xmin": 25551, "ymin": 9142}, {"ymax": 8840, "g": "114.520487,37.069531|13", "n": "邢台", "xmax": 25190, "xmin": 24735, "ymin": 8554}, {"ymax": 10068, "g": "114.893782,40.811188|13", "n": "张家口", "xmax": 25323, "xmin": 24749, "ymin": 9326}]}, {"ymin": 7150, "ymax": 8450, "g": "113.486804,34.157184|7", "n": "驻马店", "xmax": 25363, "xmin": 23996, "cities": [{"ymax": 8082, "g": "113.649644,34.75661|12", "n": "郑州", "xmax": 24836, "xmin": 24509, "ymin": 7891}, {"ymax": 8450, "g": "114.351807,36.110267|12", "n": "安阳", "xmax": 25002, "xmin": 24707, "ymin": 8140}, {"ymax": 8364, "g": "114.29777,35.755426|13", "n": "鹤壁", "xmax": 24952, "xmin": 24786, "ymin": 8203}, {"ymax": 8216, "g": "113.211836,35.234608|13", "n": "焦作", "xmax": 24710, "xmin": 24476, "ymin": 8036}, {"ymax": 8091, "g": "114.351642,34.801854|13", "n": "开封", "xmax": 25062, "xmin": 24760, "ymin": 7874}, {"ymax": 8104, "g": "112.447525,34.657368|12", "n": "洛阳", "xmax": 24566, "xmin": 24165, "ymin": 7709}, {"ymax": 7819, "g": "114.046061,33.576279|13", "n": "漯河", "xmax": 24851, "xmin": 24670, "ymin": 7668}, {"ymax": 7771, "g": "112.542842,33.01142|13", "n": "南阳", "xmax": 24747, "xmin": 24131, "ymin": 7375}, {"ymax": "", "g": "113.300849,33.745301|13", "n": "平顶山", "xmax": "", "xmin": "", "ymin": ""}, {"ymax": 8408, "g": "115.026627,35.753298|12", "n": "濮阳", "xmax": 25246, "xmin": 24977, "ymin": 8173}, {"ymax": 8108, "g": "111.181262,34.78332|13", "n": "三门峡", "xmax": 24359, "xmin": 23996, "ymin": 7706}, {"ymax": 8049, "g": "115.641886,34.438589|13", "n": "商丘", "xmax": 25363, "xmin": 24967, "ymin": 7746}, {"ymax": 8308, "g": "113.91269,35.307258|13", "n": "新乡", "xmax": 25009, "xmin": 24653, "ymin": 8053}, {"ymax": 7476, "g": "114.085491,32.128582|13", "n": "信阳", "xmax": 25210, "xmin": 24724, "ymin": 7150}, {"ymax": 7929, "g": "113.835312,34.02674|13", "n": "许昌", "xmax": 24858, "xmin": 24584, "ymin": 7742}, {"ymax": 7911, "g": "114.654102,33.623741|13", "n": "周口", "xmax": 25147, "xmin": 24807, "ymin": 7577}, {"ymax": 7700, "g": "114.049154,32.983158|13", "n": "驻马店", "xmax": 25052, "xmin": 24591, "ymin": 7377}]}, {"ymin": 10446, "ymax": 13777, "g": "128.047414,47.356592|6", "n": "伊春", "xmax": 29374, "xmin": 26349, "cities": [{"ymax": 11442, "g": "126.657717,45.773225|12", "n": "哈尔滨", "xmax": 28318, "xmin": 27329, "ymin": 10636}, {"ymax": 11698, "g": "125.02184,46.596709|12", "n": "大庆", "xmax": 27351, "xmin": 26908, "ymin": 11039}, {"ymax": 13777, "g": "124.196104,51.991789|10", "n": "大兴安岭地区", "xmax": 27620, "xmin": 26349, "ymin": 12835}, {"ymax": 11981, "g": "130.292472,47.338666|13", "n": "鹤岗", "xmax": 28815, "xmin": 28195, "ymin": 11565}, {"ymax": 12870, "g": "127.50083,50.25069|14", "n": "黑河", "xmax": 28165, "xmin": 27124, "ymin": 11733}, {"ymax": 11422, "g": "130.941767,45.32154|13", "n": "鸡西", "xmax": 29125, "xmin": 28353, "ymin": 10878}, {"ymax": 12018, "g": "130.284735,46.81378|12", "n": "佳木斯", "xmax": 29374, "xmin": 28159, "ymin": 11214}, {"ymax": 11227, "g": "129.608035,44.588521|13", "n": "牡丹江", "xmax": 28554, "xmin": 27881, "ymin": 10446}, {"ymax": 11336, "g": "131.019048,45.775005|14", "n": "七台河", "xmax": 28687, "xmin": 28289, "ymin": 11102}, {"ymax": 12172, "g": "123.987289,47.3477|13", "n": "齐齐哈尔", "xmax": 27543, "xmin": 26614, "ymin": 11301}, {"ymax": "", "g": "131.171402,46.655102|13", "n": "双鸭山", "xmax": "", "xmin": "", "ymin": ""}, {"ymax": 11898, "g": "126.989095,46.646064|13", "n": "绥化", "xmax": 27952, "xmin": 27152, "ymin": 11077}, {"ymax": 12340, "g": "128.910766,47.734685|14", "n": "伊春", "xmax": 28435, "xmin": 27751, "ymin": 11382}]}, {"ymin": 6561, "ymax": 7633, "g": "112.410562,31.209316|8", "n": "宜昌", "xmax": 25252, "xmin": 23563, "cities": [{"ymax": 7144, "g": "114.3162,30.581084|12", "n": "武汉", "xmax": 25022, "xmin": 24722, "ymin": 6793}, {"ymax": 6956, "g": "114.895594,30.384439|14", "n": "鄂州", "xmax": 25024, "xmin": 24897, "ymin": 6806}, {"ymax": 7153, "g": "109.517433,30.308978|14", "n": "恩施", "xmax": 24057, "xmin": 23563, "ymin": 6581}, {"ymax": 7206, "g": "114.906618,30.446109|14", "n": "黄冈", "xmax": 25252, "xmin": 24875, "ymin": 6732}, {"ymax": 6884, "g": "115.050683,30.216127|13", "n": "黄石", "xmax": 25116, "xmin": 24903, "ymin": 6679}, {"ymax": 7207, "g": "112.21733,31.042611|13", "n": "荆门", "xmax": 24676, "xmin": 24322, "ymin": 6899}, {"ymax": 6967, "g": "112.241866,30.332591|12", "n": "荆州", "xmax": 24807, "xmin": 24188, "ymin": 6659}, {"ymax": 6964, "g": "112.768768,30.343116|13", "n": "潜江", "xmax": 24577, "xmin": 24462, "ymin": 6821}, {"ymax": 7271, "g": "110.487231,31.595768|13", "n": "神农架林区", "xmax": 24131, "xmin": 23904, "ymin": 7128}, {"ymax": 7633, "g": "110.801229,32.636994|13", "n": "十堰", "xmax": 24262, "xmin": 23795, "ymin": 7181}, {"ymax": 7417, "g": "113.379358,31.717858|13", "n": "随州", "xmax": 24816, "xmin": 24511, "ymin": 7135}, {"ymax": 7029, "g": "113.12623,30.649047|13", "n": "天门", "xmax": 24671, "xmin": 24481, "ymin": 6896}, {"ymax": 6935, "g": "113.387448,30.293966|13", "n": "仙桃", "xmax": 24749, "xmin": 24557, "ymin": 6819}, {"ymax": 6876, "g": "114.300061,29.880657|13", "n": "咸宁", "xmax": 24999, "xmin": 24687, "ymin": 6561}, {"ymax": 7467, "g": "112.176326,32.094934|12", "n": "襄樊", "xmax": 24596, "xmin": 24084, "ymin": 7111}, {"ymax": 7269, "g": "113.935734,30.927955|13", "n": "孝感", "xmax": 24916, "xmin": 24639, "ymin": 6897}, {"ymax": 7198, "g": "111.310981,30.732758|13", "n": "宜昌", "xmax": 24371, "xmin": 23973, "ymin": 6788}]}, {"ymin": 5495, "ymax": 6833, "g": "111.720664,27.695864|7", "n": "株洲", "xmax": 24844, "xmin": 23655, "cities": [{"ymax": 6470, "g": "112.979353,28.213478|12", "n": "长沙", "xmax": 24844, "xmin": 24330, "ymin": 6270}, {"ymax": 6833, "g": "111.653718,29.012149|12", "n": "常德", "xmax": 24419, "xmin": 24024, "ymin": 6407}, {"ymax": 6024, "g": "113.037704,25.782264|13", "n": "郴州", "xmax": 24839, "xmin": 24402, "ymin": 5556}, {"ymax": 6177, "g": "112.583819,26.898164|13", "n": "衡阳", "xmax": 24631, "xmin": 24253, "ymin": 5849}, {"ymax": 6558, "g": "109.986959,27.557483|13", "n": "怀化", "xmax": 24159, "xmin": 23655, "ymin": 5789}, {"ymax": 6364, "g": "111.996396,27.741073|13", "n": "娄底", "xmax": 24466, "xmin": 24085, "ymin": 6113}, {"ymax": 6225, "g": "111.461525,27.236811|13", "n": "邵阳", "xmax": 24372, "xmin": 23879, "ymin": 5813}, {"ymax": 6325, "g": "112.935556,27.835095|13", "n": "湘潭", "xmax": 24590, "xmin": 24352, "ymin": 6146}, {"ymax": 6710, "g": "109.745746,28.317951|14", "n": "湘西州", "xmax": 24002, "xmin": 23741, "ymin": 6239}, {"ymax": 6683, "g": "112.366547,28.588088|13", "n": "益阳", "xmax": 24559, "xmin": 24074, "ymin": 6301}, {"ymax": 6031, "g": "111.614648,26.435972|13", "n": "永州", "xmax": 24452, "xmin": 24124, "ymin": 5495}, {"ymax": 6764, "g": "113.146196,29.378007|13", "n": "岳阳", "xmax": 24821, "xmin": 24421, "ymin": 6411}, {"ymax": 6750, "g": "110.48162,29.124889|13", "n": "张家界", "xmax": 24208, "xmin": 23851, "ymin": 6521}, {"ymax": 6314, "g": "113.131695,27.827433|13", "n": "株洲", "xmax": 24810, "xmin": 24563, "ymin": 5833}]}, {"ymin": 6992, "ymax": 8118, "g": "119.368489,33.013797|8", "n": "镇江", "xmax": 26526, "xmin": 25301, "cities": [{"ymax": 7463, "g": "118.778074,32.057236|12", "n": "南京", "xmax": 25927, "xmin": 25736, "ymin": 7111}, {"ymax": 7322, "g": "119.981861,31.771397|12", "n": "常州", "xmax": 26136, "xmin": 25905, "ymin": 7091}, {"ymax": 7847, "g": "119.030186,33.606513|12", "n": "淮安", "xmax": 26015, "xmin": 25705, "ymin": 7490}, {"ymax": 8118, "g": "119.173872,34.601549|12", "n": "连云港", "xmax": 26059, "xmin": 25746, "ymin": 7817}, {"ymax": 7489, "g": "120.873801,32.014665|12", "n": "南通", "xmax": 26526, "xmin": 26136, "ymin": 7208}, {"ymax": 7315, "g": "120.619907,31.317987|12", "n": "苏州", "xmax": 26393, "xmin": 26074, "ymin": 6992}, {"ymax": 7933, "g": "118.296893,33.95205|13", "n": "宿迁", "xmax": 25913, "xmin": 25644, "ymin": 7599}, {"ymax": 7620, "g": "119.919606,32.476053|13", "n": "泰州", "xmax": 26213, "xmin": 26015, "ymin": 7288}, {"ymax": 7303, "g": "120.305456,31.570037|12", "n": "无锡", "xmax": 26223, "xmin": 25987, "ymin": 7083}, {"ymax": 8070, "g": "117.188107,34.271553|12", "n": "徐州", "xmax": 25803, "xmin": 25301, "ymin": 7747}, {"ymax": 7965, "g": "120.148872,33.379862|12", "n": "盐城", "xmax": 26308, "xmin": 25974, "ymin": 7454}, {"ymax": 7671, "g": "119.427778,32.408505|13", "n": "扬州", "xmax": 26073, "xmin": 25878, "ymin": 7362}, {"ymax": 7387, "g": "119.455835,32.204409|13", "n": "镇江", "xmax": 26088, "xmin": 25868, "ymin": 7211}]}, {"ymin": 5460, "ymax": 6820, "g": "115.676082,27.757258|7", "n": "鹰潭", "xmax": 25763, "xmin": 24695, "cities": [{"ymax": 6596, "g": "115.893528,28.689578|12", "n": "南昌", "xmax": 25345, "xmin": 25100, "ymin": 6346}, {"ymax": 6428, "g": "116.360919,27.954545|13", "n": "抚州", "xmax": 25505, "xmin": 25133, "ymin": 5941}, {"ymax": 6098, "g": "114.935909,25.845296|13", "n": "赣州", "xmax": 25362, "xmin": 24768, "ymin": 5460}, {"ymax": 6298, "g": "114.992039,27.113848|13", "n": "吉安", "xmax": 25208, "xmin": 24751, "ymin": 5815}, {"ymax": 6785, "g": "117.186523,29.303563|12", "n": "景德镇", "xmax": 25594, "xmin": 25431, "ymin": 6484}, {"ymax": 6820, "g": "115.999848,29.71964|13", "n": "九江", "xmax": 25419, "xmin": 24775, "ymin": 6476}, {"ymax": 6308, "g": "113.859917,27.639544|13", "n": "萍乡", "xmax": 24847, "xmin": 24695, "ymin": 6053}, {"ymax": 6727, "g": "117.955464,28.457623|13", "n": "上饶", "xmax": 25763, "xmin": 25273, "ymin": 6258}, {"ymax": 6334, "g": "114.947117,27.822322|13", "n": "新余", "xmax": 25093, "xmin": 24893, "ymin": 6192}, {"ymax": 6578, "g": "114.400039,27.81113|13", "n": "宜春", "xmax": 25255, "xmin": 24763, "ymin": 6196}, {"ymax": 6461, "g": "117.03545,28.24131|13", "n": "鹰潭", "xmax": 25542, "xmin": 25373, "ymin": 6270}]}, {"ymin": 9696, "ymax": 11326, "g": "126.262876,43.678846|7", "n": "延边", "xmax": 28553, "xmin": 26449, "cities": [{"ymax": 10999, "g": "125.313642,43.898338|12", "n": "长春", "xmax": 27634, "xmin": 27080, "ymin": 10397}, {"ymax": 11326, "g": "122.840777,45.621086|13", "n": "白城", "xmax": 27042, "xmin": 26449, "ymin": 10686}, {"ymax": 10266, "g": "126.435798,41.945859|13", "n": "白山", "xmax": 27900, "xmin": 27422, "ymin": 9840}, {"ymax": 10814, "g": "126.564544,43.871988|12", "n": "吉林市", "xmax": 27835, "xmin": 27320, "ymin": 10190}, {"ymax": 10388, "g": "125.133686,42.923303|13", "n": "辽源", "xmax": 27362, "xmin": 27144, "ymin": 10112}, {"ymax": 10665, "g": "124.391382,43.175525|12", "n": "四平", "xmax": 27349, "xmin": 26811, "ymin": 10266}, {"ymax": 11088, "g": "124.832995,45.136049|13", "n": "松原", "xmax": 27438, "xmin": 26768, "ymin": 10615}, {"ymax": 10325, "g": "125.94265,41.736397|13", "n": "通化", "xmax": 27560, "xmin": 27236, "ymin": 9696}, {"ymax": 10773, "g": "129.485902,42.896414|13", "n": "延边", "xmax": 28553, "xmin": 27716, "ymin": 10024}]}, {"ymin": 9081, "ymax": 10465, "g": "122.753592,41.6216|8", "n": "营口", "xmax": 27351, "xmin": 25841, "cities": [{"ymax": 10332, "g": "123.432791,41.808645|12", "n": "沈阳", "xmax": 26921, "xmin": 26619, "ymin": 9793}, {"ymax": 9900, "g": "123.007763,41.118744|13", "n": "鞍山", "xmax": 26911, "xmin": 26567, "ymin": 9451}, {"ymax": 9900, "g": "123.778062,41.325838|12", "n": "本溪", "xmax": 27351, "xmin": 26872, "ymin": 9683}, {"ymax": 9476, "g": "120.446163,41.571828|13", "n": "朝阳", "xmax": 25362, "xmin": 25298, "ymin": 9397}, {"ymax": 9509, "g": "121.593478,38.94871|12", "n": "大连", "xmax": 26860, "xmin": 26292, "ymin": 9081}, {"ymax": 9781, "g": "124.338543,40.129023|12", "n": "丹东", "xmax": 27334, "xmin": 26827, "ymin": 9362}, {"ymax": 10165, "g": "123.92982,41.877304|12", "n": "抚顺", "xmax": 27285, "xmin": 26890, "ymin": 9804}, {"ymax": 10273, "g": "121.660822,42.01925|14", "n": "阜新", "xmax": 26739, "xmin": 26313, "ymin": 9936}, {"ymax": 9795, "g": "120.860758,40.74303|13", "n": "葫芦岛", "xmax": 26331, "xmin": 25921, "ymin": 9438}, {"ymax": 10063, "g": "121.147749,41.130879|13", "n": "锦州", "xmax": 26657, "xmin": 26248, "ymin": 9658}, {"ymax": 9912, "g": "123.172451,41.273339|14", "n": "辽阳", "xmax": 26894, "xmin": 26655, "ymin": 9652}, {"ymax": 9866, "g": "122.073228,41.141248|13", "n": "盘锦", "xmax": 26618, "xmin": 26413, "ymin": 9632}, {"ymax": 10465, "g": "123.85485,42.299757|13", "n": "铁岭", "xmax": 27203, "xmin": 26843, "ymin": 10021}, {"ymax": 9718, "g": "122.233391,40.668651|13", "n": "营口", "xmax": 26746, "xmin": 26496, "ymin": 9428}]}, {"ymin": 8731, "ymax": 13694, "g": "114.415868,43.468238|5", "n": "兴安盟", "xmax": 27413, "xmin": 21129, "cities": [{"ymax": 9847, "g": "111.660351,40.828319|12", "n": "呼和浩特", "xmax": 24419, "xmin": 24030, "ymin": 9335}, {"ymax": 10258, "g": "105.695683,38.843075|14", "n": "阿拉善盟", "xmax": 23237, "xmin": 21129, "ymin": 8731}, {"ymax": 10241, "g": "109.846239,40.647119|12", "n": "包头", "xmax": 24232, "xmin": 23755, "ymin": 9521}, {"ymax": 10161, "g": "107.423807,40.76918|12", "n": "巴彦淖尔", "xmax": 23897, "xmin": 22874, "ymin": 9499}, {"ymax": 10996, "g": "118.930761,42.297112|12", "n": "赤峰", "xmax": 26306, "xmin": 25302, "ymin": 9818}, {"ymax": 9702, "g": "109.993706,39.81649|12", "n": "鄂尔多斯", "xmax": 24236, "xmin": 23151, "ymin": 8789}, {"ymax": 13694, "g": "119.760822,49.201636|12", "n": "呼伦贝尔", "xmax": 27413, "xmin": 25120, "ymin": 11576}, {"ymax": 11133, "g": "122.260363,43.633756|12", "n": "通辽", "xmax": 26901, "xmin": 25926, "ymin": 10097}, {"ymax": 9424, "g": "106.831999,39.683177|13", "n": "乌海", "xmax": 23305, "xmin": 23176, "ymin": 9181}, {"ymax": 10432, "g": "113.112846,41.022363|12", "n": "乌兰察布", "xmax": 24964, "xmin": 23991, "ymin": 9497}, {"ymax": 11475, "g": "116.02734,43.939705|11", "n": "锡林郭勒盟", "xmax": 26118, "xmin": 24168, "ymin": 9902}, {"ymax": 11756, "g": "122.048167,46.083757|11", "n": "兴安盟", "xmax": 26884, "xmin": 25979, "ymin": 10695}]}, {"ymin": 8148, "ymax": 9280, "g": "106.155481,37.321323|8", "n": "中卫", "xmax": 23408, "xmin": 22677, "cities": [{"ymax": 9134, "g": "106.206479,38.502621|12", "n": "银川", "xmax": 23237, "xmin": 23013, "ymin": 8753}, {"ymax": 8521, "g": "106.285268,36.021523|13", "n": "固原", "xmax": 23256, "xmin": 22901, "ymin": 8148}, {"ymax": 9280, "g": "106.379337,39.020223|13", "n": "石嘴山", "xmax": 23263, "xmin": 23045, "ymin": 9064}, {"ymax": 8966, "g": "106.208254,37.993561|14", "n": "吴忠", "xmax": 23408, "xmin": 22960, "ymin": 8505}, {"ymax": 8826, "g": "105.196754,37.521124|14", "n": "中卫", "xmax": 23084, "xmin": 22677, "ymin": 8384}]}, {"ymin": 7205, "ymax": 9232, "g": "96.202544,35.499761|7", "n": "玉树州", "xmax": 22411, "xmin": 19441, "cities": [{"ymax": 8731, "g": "101.767921,36.640739|12", "n": "西宁", "xmax": 22159, "xmin": 21940, "ymin": 8413}, {"ymax": 8240, "g": "100.223723,34.480485|11", "n": "果洛州", "xmax": 22130, "xmin": 21086, "ymin": 7438}, {"ymax": 8661, "g": "102.085207,36.51761|11", "n": "海东地区", "xmax": 22411, "xmin": 22106, "ymin": 8204}, {"ymax": 9195, "g": "100.879802,36.960654|11", "n": "海北州", "xmax": 22318, "xmin": 21329, "ymin": 8549}, {"ymax": 8685, "g": "100.624066,36.284364|11", "n": "海南州", "xmax": 22134, "xmin": 21511, "ymin": 7991}, {"ymax": 9232, "g": "97.342625,37.373799|11", "n": "海西州", "xmax": 21697, "xmin": 19607, "ymin": 8087}, {"ymax": 8397, "g": "102.0076,35.522852|11", "n": "黄南州", "xmax": 22277, "xmin": 21893, "ymin": 7840}, {"ymax": 8425, "g": "97.013316,33.00624|14", "n": "玉树州", "xmax": 21260, "xmin": 19441, "ymin": 7205}]}, {"ymin": 7922, "ymax": 9021, "g": "118.527663,36.09929|8", "n": "淄博", "xmax": 26684, "xmin": 24966, "cities": [{"ymax": 8767, "g": "117.024967,36.682785|12", "n": "济南", "xmax": 25602, "xmin": 25271, "ymin": 8359}, {"ymax": 8979, "g": "117.968292,37.405314|12", "n": "滨州", "xmax": 25739, "xmin": 25497, "ymin": 8536}, {"ymax": 8938, "g": "118.583926,37.487121|12", "n": "东营", "xmax": 25944, "xmin": 25680, "ymin": 8604}, {"ymax": 8896, "g": "116.328161,37.460826|12", "n": "德州", "xmax": 25571, "xmin": 25170, "ymin": 8461}, {"ymax": 8315, "g": "115.46336,35.26244|13", "n": "菏泽", "xmax": 25312, "xmin": 24966, "ymin": 7967}, {"ymax": 8346, "g": "116.600798,35.402122|13", "n": "济宁", "xmax": 25569, "xmin": 25193, "ymin": 7941}, {"ymax": 8500, "g": "117.684667,36.233654|13", "n": "莱芜", "xmax": 25651, "xmin": 25511, "ymin": 8349}, {"ymax": 8627, "g": "115.986869,36.455829|12", "n": "聊城", "xmax": 25341, "xmin": 25066, "ymin": 8292}, {"ymax": 8407, "g": "118.340768,35.072409|12", "n": "临沂", "xmax": 25918, "xmin": 25531, "ymin": 7922}, {"ymax": 8660, "g": "120.384428,36.105215|12", "n": "青岛", "xmax": 26398, "xmin": 25986, "ymin": 8225}, {"ymax": 8362, "g": "119.50718,35.420225|12", "n": "日照", "xmax": 26081, "xmin": 25788, "ymin": 8074}, {"ymax": 8479, "g": "117.089415,36.188078|13", "n": "泰安", "xmax": 25657, "xmin": 25233, "ymin": 8253}, {"ymax": 8787, "g": "122.093958,37.528787|13", "n": "威海", "xmax": 26684, "xmin": 26348, "ymin": 8532}, {"ymax": 8711, "g": "119.142634,36.716115|12", "n": "潍坊", "xmax": 26094, "xmin": 25695, "ymin": 8274}, {"ymax": 9021, "g": "121.309555,37.536562|12", "n": "烟台", "xmax": 26511, "xmin": 25995, "ymin": 8502}, {"ymax": 8170, "g": "117.279305,34.807883|13", "n": "枣庄", "xmax": 25620, "xmin": 25398, "ymin": 7944}, {"ymax": 8699, "g": "118.059134,36.804685|12", "n": "淄博", "xmax": 25770, "xmin": 25558, "ymin": 8331}]}, {"ymin": 7976, "ymax": 9662, "g": "112.515496,37.866566|7", "n": "运城", "xmax": 24909, "xmin": 23966, "cities": [{"ymax": 9009, "g": "112.550864,37.890277|12", "n": "太原", "xmax": 24604, "xmin": 24247, "ymin": 8745}, {"ymax": 8654, "g": "113.120292,36.201664|12", "n": "长治", "xmax": 24730, "xmin": 24348, "ymin": 8304}, {"ymax": 9662, "g": "113.290509,40.113744|12", "n": "大同", "xmax": 24909, "xmin": 24478, "ymin": 9184}, {"ymax": 8368, "g": "112.867333,35.499834|13", "n": "晋城", "xmax": 24706, "xmin": 24339, "ymin": 8139}, {"ymax": 8919, "g": "112.738514,37.693362|13", "n": "晋中", "xmax": 24817, "xmin": 24224, "ymin": 8524}, {"ymax": 8603, "g": "111.538788,36.099745|13", "n": "临汾", "xmax": 24477, "xmin": 23999, "ymin": 8188}, {"ymax": 9095, "g": "111.143157,37.527316|14", "n": "吕梁", "xmax": 24424, "xmin": 23999, "ymin": 8548}, {"ymax": 9536, "g": "112.479928,39.337672|13", "n": "朔州", "xmax": 24694, "xmin": 24330, "ymin": 9195}, {"ymax": 9356, "g": "112.727939,38.461031|12", "n": "忻州", "xmax": 24780, "xmin": 24123, "ymin": 8930}, {"ymax": 9038, "g": "113.569238,37.869529|13", "n": "阳泉", "xmax": 24797, "xmin": 24552, "ymin": 8801}, {"ymax": 8304, "g": "111.006854,35.038859|13", "n": "运城", "xmax": 24370, "xmin": 23966, "ymin": 7976}]}, {"ymin": 7231, "ymax": 9334, "g": "109.503789,35.860026|7", "n": "榆林", "xmax": 24188, "xmin": 22937, "cities": [{"ymax": 8018, "g": "108.953098,34.2778|12", "n": "西安", "xmax": 23879, "xmin": 23402, "ymin": 7743}, {"ymax": 7781, "g": "109.038045,32.70437|13", "n": "安康", "xmax": 23962, "xmin": 23488, "ymin": 7231}, {"ymax": 8113, "g": "107.170645,34.364081|12", "n": "宝鸡", "xmax": 23495, "xmin": 23115, "ymin": 7713}, {"ymax": 7791, "g": "107.045478,33.081569|13", "n": "汉中", "xmax": 23544, "xmin": 22938, "ymin": 7344}, {"ymax": 7936, "g": "109.934208,33.873907|13", "n": "商洛", "xmax": 24143, "xmin": 23608, "ymin": 7588}, {"ymax": 8239, "g": "108.968067,34.908368|13", "n": "铜川", "xmax": 23808, "xmin": 23609, "ymin": 8034}, {"ymax": 8312, "g": "109.483933,34.502358|13", "n": "渭南", "xmax": 24049, "xmin": 23692, "ymin": 7878}, {"ymax": 8230, "g": "108.707509,34.345373|13", "n": "咸阳", "xmax": 23739, "xmin": 23407, "ymin": 7874}, {"ymax": 8757, "g": "109.50051,36.60332|13", "n": "延安", "xmax": 24038, "xmin": 23409, "ymin": 8177}, {"ymax": 9334, "g": "109.745926,38.279439|12", "n": "榆林", "xmax": 24188, "xmin": 23323, "ymin": 8572}]}, {"ymin": 5833, "ymax": 7904, "g": "102.89916,30.367481|7", "n": "自贡", "xmax": 23601, "xmin": 21168, "cities": [{"ymax": 7163, "g": "104.067923,30.679943|12", "n": "成都", "xmax": 22807, "xmin": 22401, "ymin": 6825}, {"ymax": 7904, "g": "102.228565,31.905763|15", "n": "阿坝州", "xmax": 22708, "xmin": 21858, "ymin": 6951}, {"ymax": 7496, "g": "106.757916,31.869189|14", "n": "巴中", "xmax": 23431, "xmin": 23128, "ymin": 7116}, {"ymax": 7393, "g": "107.494973,31.214199|14", "n": "达州", "xmax": 23601, "xmin": 23193, "ymin": 6883}, {"ymax": 7230, "g": "104.402398,31.13114|13", "n": "德阳", "xmax": 22868, "xmin": 22569, "ymin": 6933}, {"ymax": 7874, "g": "101.969232,30.055144|15", "n": "甘孜州", "xmax": 22286, "xmin": 21168, "ymin": 6297}, {"ymax": 7016, "g": "106.63572,30.463984|13", "n": "广安", "xmax": 23333, "xmin": 23036, "ymin": 6806}, {"ymax": 7546, "g": "105.819687,32.44104|13", "n": "广元", "xmax": 23214, "xmin": 22747, "ymin": 7186}, {"ymax": 6784, "g": "103.760824,29.600958|13", "n": "乐山", "xmax": 22668, "xmin": 22376, "ymin": 6410}, {"ymax": 6628, "g": "102.259591,27.892393|14", "n": "凉山州", "xmax": 22586, "xmin": 21757, "ymin": 5833}, {"ymax": 6634, "g": "105.44397,28.89593|14", "n": "泸州", "xmax": 23131, "xmin": 22862, "ymin": 6224}, {"ymax": 7268, "g": "106.105554,30.800965|13", "n": "南充", "xmax": 23258, "xmin": 22927, "ymin": 6916}, {"ymax": 6892, "g": "103.84143,30.061115|13", "n": "眉山", "xmax": 22722, "xmin": 22363, "ymin": 6652}, {"ymax": 7574, "g": "104.705519,31.504701|12", "n": "绵阳", "xmax": 22988, "xmin": 22558, "ymin": 6979}, {"ymax": 6812, "g": "105.073056,29.599462|13", "n": "内江", "xmax": 22927, "xmin": 22672, "ymin": 6599}, {"ymax": 6147, "g": "101.722423,26.587571|14", "n": "攀枝花", "xmax": 22232, "xmin": 21991, "ymin": 5841}, {"ymax": 7093, "g": "105.564888,30.557491|12", "n": "遂宁", "xmax": 23048, "xmin": 22843, "ymin": 6846}, {"ymax": 7037, "g": "103.009356,29.999716|13", "n": "雅安", "xmax": 22481, "xmin": 22164, "ymin": 6516}, {"ymax": 6619, "g": "104.633019,28.769675|13", "n": "宜宾", "xmax": 22908, "xmin": 22529, "ymin": 6268}, {"ymax": 6963, "g": "104.63593,30.132191|13", "n": "资阳", "xmax": 22994, "xmin": 22655, "ymin": 6721}, {"ymax": 6711, "g": "104.776071,29.359157|13", "n": "自贡", "xmax": 22889, "xmin": 22624, "ymin": 6534}]}, {"ymin": 6027, "ymax": 8481, "g": "89.137982,31.367315|6", "n": "山南地区", "xmax": 21550, "xmin": 17046, "cities": [{"ymax": 7067, "g": "91.111891,29.662557|13", "n": "拉萨", "xmax": 20139, "xmin": 19515, "ymin": 6612}, {"ymax": 8314, "g": "81.107669,30.404557|11", "n": "阿里地区", "xmax": 18771, "xmin": 17046, "ymin": 6721}, {"ymax": 7458, "g": "97.185582,31.140576|15", "n": "昌都地区", "xmax": 21550, "xmin": 20351, "ymin": 6414}, {"ymax": 6970, "g": "94.349985,29.666941|11", "n": "林芝地区", "xmax": 21472, "xmin": 20039, "ymin": 6199}, {"ymax": 8481, "g": "92.067018,31.48068|14", "n": "那曲地区", "xmax": 20661, "xmin": 18493, "ymin": 6786}, {"ymax": 7257, "g": "88.891486,29.269023|14", "n": "日喀则地区", "xmax": 19645, "xmin": 17861, "ymin": 6114}, {"ymax": 6758, "g": "91.750644,29.229027|11", "n": "山南地区", "xmax": 20517, "xmin": 19584, "ymin": 6027}]}, {"ymin": 7910, "ymax": 12253, "g": "85.614899,42.127001|6", "n": "伊犁州", "xmax": 20958, "xmin": 15980, "cities": [{"ymax": 10922, "g": "87.564988,43.84038|12", "n": "乌鲁木齐", "xmax": 19347, "xmin": 18871, "ymin": 10294}, {"ymax": 9720, "g": "81.291737,40.61568|13", "n": "阿拉尔", "xmax": 17820, "xmin": 17523, "ymin": 9554}, {"ymax": 10214, "g": "80.269846,41.171731|12", "n": "阿克苏地区", "xmax": 18284, "xmin": 16966, "ymin": 9301}, {"ymax": 12253, "g": "88.137915,47.839744|13", "n": "阿勒泰地区", "xmax": 19803, "xmin": 18597, "ymin": 10922}, {"ymax": 10486, "g": "86.121688,41.771362|12", "n": "巴音郭楞", "xmax": 20410, "xmin": 17932, "ymin": 8255}, {"ymax": 11041, "g": "82.052436,44.913651|11", "n": "博尔塔拉州", "xmax": 18222, "xmin": 17370, "ymin": 10619}, {"ymax": 11071, "g": "87.296038,44.007058|13", "n": "昌吉州", "xmax": 19914, "xmin": 19088, "ymin": 10440}, {"ymax": 10949, "g": "93.528355,42.858596|13", "n": "哈密地区", "xmax": 20958, "xmin": 19825, "ymin": 9665}, {"ymax": 9348, "g": "79.930239,37.116774|13", "n": "和田地区", "xmax": 18464, "xmin": 16830, "ymin": 7910}, {"ymax": 9524, "g": "75.992973,39.470627|12", "n": "喀什地区", "xmax": 17366, "xmin": 16190, "ymin": 8205}, {"ymax": 11297, "g": "84.88118,45.594331|13", "n": "克拉玛依", "xmax": 18707, "xmin": 18384, "ymin": 10823}, {"ymax": 9851, "g": "76.137564,39.750346|11", "n": "克孜勒苏州", "xmax": 17151, "xmin": 15980, "ymin": 8798}, {"ymax": 10757, "g": "86.041865,44.308259|13", "n": "石河子", "xmax": 18736, "xmin": 18678, "ymin": 10655}, {"ymax": 11620, "g": "82.974881,46.758684|12", "n": "塔城地区", "xmax": 18990, "xmin": 17884, "ymin": 10462}, {"ymax": 9487, "g": "79.198155,39.889223|13", "n": "图木舒克", "xmax": 17309, "xmin": 17102, "ymin": 9343}, {"ymax": 10508, "g": "89.181595,42.96047|13", "n": "吐鲁番地区", "xmax": 19985, "xmin": 18973, "ymin": 9790}, {"ymax": 10798, "g": "87.565449,44.368899|13", "n": "五家渠", "xmax": 19073, "xmin": 18997, "ymin": 10619}, {"ymax": 10873, "g": "81.297854,43.922248|11", "n": "伊犁州", "xmax": 18470, "xmin": 17430, "ymin": 10100}]}, {"ymin": 4675, "ymax": 6615, "g": "101.592952,24.864213|7", "n": "玉溪", "xmax": 23091, "xmin": 21206, "cities": [{"ymax": 5953, "g": "102.714601,25.049153|12", "n": "昆明", "xmax": 22542, "xmin": 22215, "ymin": 5436}, {"ymax": 5787, "g": "99.177996,25.120489|13", "n": "保山", "xmax": 21753, "xmin": 21328, "ymin": 5373}, {"ymax": 5942, "g": "101.529382,25.066356|13", "n": "楚雄州", "xmax": 22283, "xmin": 21900, "ymin": 5397}, {"ymax": 5990, "g": "100.223675,25.5969|14", "n": "大理州", "xmax": 21971, "xmin": 21496, "ymin": 5501}, {"ymax": 5662, "g": "98.589434,24.44124|14", "n": "德宏州", "xmax": 21466, "xmin": 21206, "ymin": 5306}, {"ymax": 6615, "g": "99.713682,27.831029|14", "n": "迪庆州", "xmax": 21810, "xmin": 21438, "ymin": 6031}, {"ymax": 5526, "g": "103.384065,23.367718|11", "n": "红河州", "xmax": 22674, "xmin": 22135, "ymin": 4978}, {"ymax": 6289, "g": "100.229628,26.875351|13", "n": "丽江", "xmax": 22072, "xmin": 21609, "ymin": 5818}, {"ymax": "", "g": "100.092613,23.887806|14", "n": "临沧", "xmax": "", "xmin": "", "ymin": ""}, {"ymax": 6404, "g": "98.859932,25.860677|14", "n": "怒江州", "xmax": 21666, "xmin": 21337, "ymin": 5713}, {"ymax": "", "g": "100.980058,22.788778|14", "n": "普洱", "xmax": "", "xmin": "", "ymin": ""}, {"ymax": 6076, "g": "103.782539,25.520758|12", "n": "曲靖", "xmax": 22793, "xmin": 22407, "ymin": 5427}, {"ymax": 6471, "g": "103.725021,27.340633|13", "n": "昭通", "xmax": 22899, "xmin": 22368, "ymin": 5951}, {"ymax": 5453, "g": "104.089112,23.401781|14", "n": "文山", "xmax": 23091, "xmin": 22520, "ymin": 5035}, {"ymax": 5013, "g": "100.803038,22.009433|13", "n": "西双版纳", "xmax": 22144, "xmin": 21731, "ymin": 4675}, {"ymax": 5571, "g": "102.545068,24.370447|13", "n": "玉溪", "xmax": 22429, "xmin": 22021, "ymin": 5182}]}, {"ymin": 6101, "ymax": 7096, "g": "119.957202,29.159494|8", "n": "舟山", "xmax": 26556, "xmin": 25662, "cities": [{"ymax": 6944, "g": "120.219375,30.259244|12", "n": "杭州", "xmax": 26249, "xmin": 25732, "ymin": 6600}, {"ymax": 7098, "g": "120.137243,30.877925|12", "n": "湖州", "xmax": 26198, "xmin": 25926, "ymin": 6895}, {"ymax": 7061, "g": "120.760428,30.773992|13", "n": "嘉兴", "xmax": 26427, "xmin": 26156, "ymin": 6863}, {"ymax": 6722, "g": "119.652576,29.102899|12", "n": "金华", "xmax": 26262, "xmin": 25924, "ymin": 6435}, {"ymax": 6541, "g": "119.929576,28.4563|13", "n": "丽水", "xmax": 26187, "xmin": 25809, "ymin": 6165}, {"ymax": 6915, "g": "121.579006,29.885259|12", "n": "宁波", "xmax": 26594, "xmin": 26282, "ymin": 6514}, {"ymax": 6676, "g": "118.875842,28.95691|12", "n": "衢州", "xmax": 25950, "xmin": 25663, "ymin": 6366}, {"ymax": 6873, "g": "120.592467,30.002365|13", "n": "绍兴", "xmax": 26359, "xmin": 26068, "ymin": 6609}, {"ymax": 6637, "g": "121.440613,28.668283|13", "n": "台州", "xmax": 26522, "xmin": 26155, "ymin": 6307}, {"ymax": 6457, "g": "120.690635,28.002838|12", "n": "温州", "xmax": 26390, "xmin": 26010, "ymin": 6067}, {"ymax": 7028, "g": "122.169872,30.03601|13", "n": "舟山", "xmax": 26742, "xmin": 26423, "ymin": 6689}]}]}